museval/__init__.py
museval/aggregate.py
museval/cli.py
museval/metrics.py
museval/musdb.schema.json
museval/version.py
museval-0.4.1.dist-info/LICENSE
museval-0.4.1.dist-info/METADATA
museval-0.4.1.dist-info/WHEEL
museval-0.4.1.dist-info/entry_points.txt
museval-0.4.1.dist-info/top_level.txt
museval-0.4.1.dist-info/RECORD
