Metadata-Version: 2.1
Name: museval
Version: 0.4.1
Summary: Evaluation tools for the SIGSEP MUS database
Home-page: https://github.com/sigsep/sigsep-mus-eval
Author: Fabian-Robert Stoeter
Author-email: mail@faroit.com
License: MIT
Classifier: Development Status :: 4 - Beta
Classifier: Environment :: Console
Classifier: Environment :: Plugins
Classifier: Intended Audience :: Telecommunications Industry
Classifier: Intended Audience :: Science/Research
Classifier: Programming Language :: Python :: 3.6
Classifier: Programming Language :: Python :: 3.7
Classifier: Topic :: Multimedia :: Sound/Audio :: Analysis
Classifier: Topic :: Multimedia :: Sound/Audio :: Sound Synthesis
License-File: LICENSE
Requires-Dist: musdb (>=0.4.0)
Requires-Dist: pandas (>=1.0.1)
Requires-Dist: numpy
Requires-Dist: scipy
Requires-Dist: simplejson (>=3.19.0)
Requires-Dist: soundfile
Requires-Dist: jsonschema
Provides-Extra: dev
Requires-Dist: check-manifest ; extra == 'dev'
Provides-Extra: docs
Requires-Dist: sphinx ; extra == 'docs'
Requires-Dist: sphinx-rtd-theme ; extra == 'docs'
Requires-Dist: recommonmark ; extra == 'docs'
Requires-Dist: numpydoc ; extra == 'docs'
Provides-Extra: tests
Requires-Dist: pytest ; extra == 'tests'
